KratosMultiphysics/MeshingApplication/__init__.py
KratosMultiphysics/MeshingApplication/gradual_variable_interpolation_process.py
KratosMultiphysics/MeshingApplication/mmg_process.py
KratosMultiphysics/MeshingApplication/multiscale_refining_process.py
KratosMultiphysics/MeshingApplication/python_registry_lists.py
KratosMultiphysics/MeshingApplication/modelers/convert_linear_tetrahedra_to_quadratic_modeler.py
KratosMultiphysics/.libs/KratosMeshingApplication.pyd
KratosMultiphysics/.libs/KratosMeshingCore.dll
KratosMultiphysics/.libs/KratosMeshingCore.lib
kratosmeshingapplication-10.4.0.dist-info/METADATA
kratosmeshingapplication-10.4.0.dist-info/WHEEL
kratosmeshingapplication-10.4.0.dist-info/RECORD
